<?xml version="1.0" encoding="utf-8"?>
<publishData>
  <publishProfile publishUrl="\\TESTWEB\inetpub\wwwroot\ReportBuilderAjax" deleteExistingFiles="False" ftpAnonymousLogin="False" ftpPassiveMode="True" msdeploySite="" msdeploySiteID="" msdeployRemoteSitePhysicalPath="" msdeployAllowUntrustedCertificate="False" msdeploySkipExtraFilesOnServer="True" msdeployMarkAsApp="False" profileName="SystemTest" publishMethod="FileSystem" replaceMatchingFiles="True" userName="" savePWD="False" userPWD="" SelectedForPublish="True">
    <file relUrl="images/top_filter_bg.png" publishTime="08/28/2012 12:09:15" />
    <file relUrl="images/LeftYellowBttn.png" publishTime="08/28/2012 12:09:15" />
    <file relUrl="images/gray_left_sort.png" publishTime="08/28/2012 12:09:14" />
    <file relUrl="images/CenterWhiteTab.png" publishTime="08/28/2012 12:09:15" />
    <file relUrl="Services/ReportDeliveryService.svc" publishTime="08/28/2012 12:09:16" />
    <file relUrl="images/top_right_active_bg_report.png" publishTime="08/28/2012 12:09:15" />
    <file relUrl="js/TabsControlManager.js" publishTime="08/28/2012 12:09:16" />
    <file relUrl="images/right_corner_group_active.png" publishTime="08/28/2012 12:09:14" />
    <file relUrl="GetFile.aspx" publishTime="08/28/2012 12:09:13" />
    <file relUrl="images/radio_center_black2.png" publishTime="08/28/2012 12:09:15" />
    <file relUrl="Templates/ReportBuilderForm.htm" publishTime="08/28/2012 14:41:51" />
    <file relUrl="images/top_line.png" publishTime="08/28/2012 12:09:15" />
    <file relUrl="images/top_dotted_border.png" publishTime="08/28/2012 12:09:15" />
    <file relUrl="images/bottom_left_active_bg_report.png" publishTime="08/28/2012 12:09:14" />
    <file relUrl="bin/FilterService.dll" publishTime="08/28/2012 21:45:03" />
    <file relUrl="images/left_corner_filter_textbox.png" publishTime="08/28/2012 12:09:15" />
    <file relUrl="images/next_page_delivered_history.png" publishTime="08/28/2012 12:09:14" />
    <file relUrl="images/left_corner_tab_active.png" publishTime="08/28/2012 12:09:15" />
    <file relUrl="images/Logout.png" publishTime="08/28/2012 12:09:15" />
    <file relUrl="js/Common/jquery.formatCurrency.js" publishTime="08/28/2012 12:09:15" />
    <file relUrl="css/ui-lightness/images/ui-bg_highlight-soft_75_ffe45c_1x100.png" publishTime="08/28/2012 12:09:16" />
    <file relUrl="images/right_corner_top_filter.png" publishTime="08/28/2012 12:09:15" />
    <file relUrl="js/Common/jquery-1.3.2.js" publishTime="08/28/2012 12:09:15" />
    <file relUrl="images/CenterWhiteTab2.png" publishTime="08/28/2012 12:09:15" />
    <file relUrl="images/login_error.png" publishTime="08/28/2012 12:09:14" />
    <file relUrl="images/XLSradio.png" publishTime="08/28/2012 12:09:15" />
    <file relUrl="images/nextReportBtn.png" publishTime="08/28/2012 12:09:15" />
    <file relUrl="images/LogoImage.png" publishTime="08/28/2012 12:09:14" />
    <file relUrl="images/center_numder_history_page.png" publishTime="08/28/2012 12:09:15" />
    <file relUrl="images/RightBlackTab.png" publishTime="08/28/2012 12:09:15" />
    <file relUrl="js/Consts.js" publishTime="08/28/2012 12:09:15" />
    <file relUrl="images/DropDownRight2.png" publishTime="08/28/2012 12:09:15" />
    <file relUrl="images/as_grid_input.png" publishTime="08/28/2012 12:09:15" />
    <file relUrl="images/bottom_right_active_bg_report.png" publishTime="08/28/2012 12:09:15" />
    <file relUrl="images/bottom_combobox_filter_bg.png" publishTime="08/28/2012 12:09:14" />
    <file relUrl="images/switchClient_popin_switch.png" publishTime="08/28/2012 12:09:15" />
    <file relUrl="js/HierarchyControl.js" publishTime="08/28/2012 12:09:16" />
    <file relUrl="images/leftBg.png" publishTime="08/28/2012 12:09:14" />
    <file relUrl="images/CenterGrayButton.png" publishTime="08/28/2012 12:09:15" />
    <file relUrl="HttpHandlers/ReportBuilderHandler.ashx" publishTime="08/28/2012 12:09:13" />
    <file relUrl="images/login_background.png" publishTime="08/28/2012 12:09:15" />
    <file relUrl="images/left_corner_group_inactive.png" publishTime="08/28/2012 12:09:15" />
    <file relUrl="images/DropDown_filter_right_top_radius.png" publishTime="08/28/2012 12:09:15" />
    <file relUrl="images/as_grid_comment_input_left.png" publishTime="08/28/2012 12:09:15" />
    <file relUrl="js/ReportLayout.js" publishTime="08/28/2012 12:09:15" />
    <file relUrl="images/PDFradio.png" publishTime="08/28/2012 12:09:14" />
    <file relUrl="images/RightWhiteBttn2.png" publishTime="08/28/2012 12:09:15" />
    <file relUrl="images/center_active_bg_report.png" publishTime="08/28/2012 12:09:15" />
    <file relUrl="js/Common/TemplateManager.js" publishTime="08/28/2012 12:09:15" />
    <file relUrl="images/SaveReport.png" publishTime="08/28/2012 12:09:15" />
    <file relUrl="images/ScrollLeftIcon.png" publishTime="08/28/2012 12:09:15" />
    <file relUrl="images/dropDownLeft.png" publishTime="08/28/2012 12:09:15" />
    <file relUrl="js/ReleaseNotes.js" publishTime="08/28/2012 12:09:16" />
    <file relUrl="images/left_corner_as_grid_bottom.png" publishTime="08/28/2012 12:09:15" />
    <file relUrl="Fonts/semibold/MyriadPro-Semibold.eot" publishTime="08/28/2012 12:09:18" />
    <file relUrl="images/RightWhiteLoginBttn.png" publishTime="08/28/2012 12:09:15" />
    <file relUrl="images/combobox_options_top_bg.png" publishTime="08/28/2012 12:09:15" />
    <file relUrl="images/active_folder.png" publishTime="08/28/2012 12:09:15" />
    <file relUrl="images/center_hover_bg_report.png" publishTime="08/28/2012 12:09:15" />
    <file relUrl="images/as_main_button_Ok.png" publishTime="08/28/2012 12:09:15" />
    <file relUrl="images/black_right_sort.png" publishTime="08/28/2012 12:09:15" />
    <file relUrl="Templates/ReportLayoutGroups.htm" publishTime="08/28/2012 12:09:13" />
    <file relUrl="images/button_ok_change_field_name.png" publishTime="08/28/2012 12:09:15" />
    <file relUrl="images/bottom_left.png" publishTime="08/28/2012 12:09:15" />
    <file relUrl="images/right_corner_tab_sheduler.png" publishTime="08/28/2012 12:09:15" />
    <file relUrl="HttpHandlers/ReportBuilderService.svc" publishTime="08/28/2012 12:09:13" />
    <file relUrl="Templates/ReportLayoutSorting.htm" publishTime="08/28/2012 12:09:13" />
    <file relUrl="Web.config" publishTime="08/28/2012 21:45:18" />
    <file relUrl="Templates/LossRunSummaryFilterTemplate.htm" publishTime="08/28/2012 12:09:13" />
    <file relUrl="images/RadioInactive.png" publishTime="08/28/2012 12:09:14" />
    <file relUrl="js/Common/jquery.watermark.min.js" publishTime="08/28/2012 12:09:16" />
    <file relUrl="js/Common/ControlLibrary/ClassLibraryInternalTypes.js" publishTime="08/28/2012 12:09:15" />
    <file relUrl="Fonts/ptn77f-webfont.ttf" publishTime="08/28/2012 12:09:18" />
    <file relUrl="images/top_left_dotted_border.png" publishTime="08/28/2012 12:09:15" />
    <file relUrl="images/PdfIcon.png" publishTime="08/28/2012 12:09:14" />
    <file relUrl="images/RightSaveBttn.png" publishTime="08/28/2012 12:09:15" />
    <file relUrl="images/left_corner_combobox.png" publishTime="08/28/2012 12:09:15" />
    <file relUrl="js/Common/ControlLibrary/TextBoxControl.js" publishTime="08/28/2012 12:09:16" />
    <file relUrl="images/LeftCenterBg.png" publishTime="08/28/2012 12:09:15" />
    <file relUrl="images/BackgroundShape.png" publishTime="08/28/2012 12:09:15" />
    <file relUrl="css/ui-lightness/jquery-ui-1.8.16.custom.css" publishTime="08/28/2012 12:09:16" />
    <file relUrl="Fonts/regular/MyriadPro-Regular.ttf" publishTime="08/28/2012 12:09:19" />
    <file relUrl="js/FilterDataManager.js" publishTime="08/28/2012 12:09:15" />
    <file relUrl="images/left_corner_top_sheduler.png" publishTime="08/28/2012 12:09:15" />
    <file relUrl="images/as_grid_input_left.png" publishTime="08/28/2012 12:09:15" />
    <file relUrl="images/bottom_line.png" publishTime="08/28/2012 12:09:15" />
    <file relUrl="images/top_right_dotted_border.png" publishTime="08/28/2012 12:09:15" />
    <file relUrl="images/RadioInactive2.png" publishTime="08/28/2012 12:09:15" />
    <file relUrl="images/Save.png" publishTime="08/28/2012 12:09:15" />
    <file relUrl="images/top_right.png" publishTime="08/28/2012 12:09:15" />
    <file relUrl="Fonts/ptsans/PTSans-NarrowBold.afm" publishTime="08/28/2012 12:09:21" />
    <file relUrl="images/bottom_left_active_report_fields.png" publishTime="08/28/2012 12:09:15" />
    <file relUrl="images/Recucle.png" publishTime="08/28/2012 12:09:15" />
    <file relUrl="images/BasicFilterBg.png" publishTime="08/28/2012 12:09:15" />
    <file relUrl="images/YellowXButton.png" publishTime="08/28/2012 12:09:15" />
    <file relUrl="images/YellowPlusButton.png" publishTime="08/28/2012 12:09:14" />
    <file relUrl="images/previous_page_delivered_history.png" publishTime="08/28/2012 12:09:15" />
    <file relUrl="images/CenterWhiteLoginBttn.png" publishTime="08/28/2012 12:09:15" />
    <file relUrl="images/top_main_bg_report.png" publishTime="08/28/2012 12:09:14" />
    <file relUrl="Fonts/semibold/MyriadPro-Semibold.afm" publishTime="08/28/2012 12:09:18" />
    <file relUrl="images/combobox_overlay_option_bg.png" publishTime="08/28/2012 12:09:15" />
    <file relUrl="images/DropDown_left_bottom_radius.png" publishTime="08/28/2012 12:09:15" />
    <file relUrl="images/combobox_filter_button.png" publishTime="08/28/2012 12:09:14" />
    <file relUrl="images/XlsIcon.png" publishTime="08/28/2012 12:09:14" />
    <file relUrl="images/right_corner_tab_active.png" publishTime="08/28/2012 12:09:15" />
    <file relUrl="Fonts/myriadpro-bold-webfont.woff" publishTime="08/28/2012 12:09:18" />
    <file relUrl="images/SaveReportAsNew.png" publishTime="08/28/2012 12:09:15" />
    <file relUrl="images/left_corner_bottom_combobox.png" publishTime="08/28/2012 12:09:15" />
    <file relUrl="images/pencil.png" publishTime="08/28/2012 12:09:14" />
    <file relUrl="images/GrayGridBg.png" publishTime="08/28/2012 12:09:15" />
    <file relUrl="CompanyLogo/ccmsi.png" publishTime="08/28/2012 12:09:16" />
    <file relUrl="js/Common/Plupload/plupload.silverlight.xap" publishTime="08/28/2012 12:09:15" />
    <file relUrl="css/ui-lightness/images/ui-bg_diagonals-thick_18_b81900_40x40.png" publishTime="08/28/2012 12:09:16" />
    <file relUrl="images/BottomMainBg.png" publishTime="08/28/2012 12:09:15" />
    <file relUrl="ReportBuilder.aspx" publishTime="08/28/2012 12:09:21" />
    <file relUrl="images/center_right.png" publishTime="08/28/2012 12:09:15" />
    <file relUrl="images/rn_top_border.png" publishTime="08/28/2012 12:09:14" />
    <file relUrl="images/left_corner_tab_sheduler_active.png" publishTime="08/28/2012 12:09:14" />
    <file relUrl="Fonts/ptn77f-webfont.svg" publishTime="08/28/2012 12:09:18" />
    <file relUrl="images/as_grid3_bottom.png" publishTime="08/28/2012 12:09:15" />
    <file relUrl="images/center_hover_blue_report.png" publishTime="08/28/2012 12:09:15" />
    <file relUrl="images/SavePopUpCloud.png" publishTime="08/28/2012 12:09:15" />
    <file relUrl="images/YellowAddTimeButton.png" publishTime="08/28/2012 12:09:15" />
    <file relUrl="images/sort_desc.png" publishTime="08/28/2012 12:09:15" />
    <file relUrl="bin/ReportBuilderAjax.Web.dll" publishTime="08/28/2012 21:45:05" />
    <file relUrl="images/combobox_bg.png" publishTime="08/28/2012 12:09:15" />
    <file relUrl="images/CenterGreyHeaderBackground.png" publishTime="08/28/2012 12:09:15" />
    <file relUrl="images/combobox_button.png" publishTime="08/28/2012 12:09:15" />
    <file relUrl="images/LeftWhiteTab2.png" publishTime="08/28/2012 12:09:15" />
    <file relUrl="images/MainLeftShadow.png" publishTime="08/28/2012 12:09:15" />
    <file relUrl="js/Common/jquery.block.ui.js" publishTime="08/28/2012 12:09:15" />
    <file relUrl="images/number_of_reports.png" publishTime="08/28/2012 12:09:15" />
    <file relUrl="images/RightBlackBttn.png" publishTime="08/28/2012 12:09:15" />
    <file relUrl="bin/FilterService.pdb" publishTime="08/28/2012 21:45:03" />
    <file relUrl="images/XlsIcon2.png" publishTime="08/28/2012 12:09:15" />
    <file relUrl="images/top_left_active_bg_report.png" publishTime="08/28/2012 12:09:14" />
    <file relUrl="images/GridBottomShadow.png" publishTime="08/28/2012 12:09:15" />
    <file relUrl="images/gray_right_sort.png" publishTime="08/28/2012 12:09:15" />
    <file relUrl="Templates/AddSchedule.htm" publishTime="08/28/2012 12:09:13" />
    <file relUrl="images/tab_sheduler_bg.png" publishTime="08/28/2012 12:09:15" />
    <file relUrl="images/BottomButtonsBg2.png" publishTime="08/28/2012 12:09:14" />
    <file relUrl="images/LogoutIcon.png" publishTime="08/28/2012 12:09:15" />
    <file relUrl="images/clear_hierarchy.png" publishTime="08/28/2012 12:09:15" />
    <file relUrl="Templates/ReportSelectForm.htm" publishTime="08/28/2012 14:41:51" />
    <file relUrl="Fonts/ptsans/PTSans-NarrowBold.ttf" publishTime="08/28/2012 12:09:21" />
    <file relUrl="js/Common/jquery.maskMoney.js" publishTime="08/28/2012 12:09:15" />
    <file relUrl="js/Common/ControlLibrary/CheckBoxControl.js" publishTime="08/28/2012 12:09:15" />
    <file relUrl="js/Common/ControlLibrary/AsOfDateControl.js" publishTime="08/28/2012 12:09:15" />
    <file relUrl="images/login_input_password_text.png" publishTime="08/28/2012 12:09:15" />
    <file relUrl="js/Common/setFrameSizeByContent.js" publishTime="08/28/2012 12:09:15" />
    <file relUrl="images/DropDown_filter_right_border.png" publishTime="08/28/2012 12:09:15" />
    <file relUrl="images/RightLastXDays.png" publishTime="08/28/2012 12:09:15" />
    <file relUrl="js/Common/Plupload/gears_init.js" publishTime="08/28/2012 12:09:15" />
    <file relUrl="images/reportSeparator.png" publishTime="08/28/2012 12:09:15" />
    <file relUrl="images/MainRightShadow2.png" publishTime="08/28/2012 12:09:15" />
    <file relUrl="images/mainBg2.png" publishTime="08/28/2012 12:09:15" />
    <file relUrl="js/Common/ControlLibrary/RadioButtonControl.js" publishTime="08/28/2012 12:09:16" />
    <file relUrl="js/Common/jquery-ui-1.7.1.custom.min.js" publishTime="08/28/2012 12:09:15" />
    <file relUrl="images/left_corner_bottom_sheduler.png" publishTime="08/28/2012 12:09:15" />
    <file relUrl="Fonts/myriadpro-semibold-webfont.ttf" publishTime="08/28/2012 12:09:19" />
    <file relUrl="js/Common/ControlLibrary/CheckBoxSetControl.js" publishTime="08/28/2012 12:09:16" />
    <file relUrl="Fonts/myriadpro-bold-webfont.svg" publishTime="08/28/2012 12:09:18" />
    <file relUrl="images/radio_center_black3.png" publishTime="08/28/2012 12:09:14" />
    <file relUrl="js/Common/ControlLibrary/DeliveryMethodRadioButton.js" publishTime="08/28/2012 12:09:16" />
    <file relUrl="images/bottom_right_hover_blue_report.png" publishTime="08/28/2012 12:09:15" />
    <file relUrl="images/top_hover_blue_report.png" publishTime="08/28/2012 12:09:15" />
    <file relUrl="images/top_right_hover_blue_report.png" publishTime="08/28/2012 12:09:15" />
    <file relUrl="js/ReportTypes.js" publishTime="08/28/2012 12:09:16" />
    <file relUrl="images/left_dotted_border.png" publishTime="08/28/2012 12:09:15" />
    <file relUrl="images/group_active_bg.png" publishTime="08/28/2012 12:09:15" />
    <file relUrl="css/ui-lightness/images/ui-bg_glass_65_ffffff_1x400.png" publishTime="08/28/2012 12:09:16" />
    <file relUrl="js/Common/ControlLibrary/newDropDownControl.js" publishTime="08/28/2012 12:09:15" />
    <file relUrl="images/ClearFilter.png" publishTime="08/28/2012 12:09:14" />
    <file relUrl="images/RightBlackTab2.png" publishTime="08/28/2012 12:09:15" />
    <file relUrl="images/top_sheduler_bg.png" publishTime="08/28/2012 12:09:15" />
    <file relUrl="images/radio_center_white2.png" publishTime="08/28/2012 12:09:15" />
    <file relUrl="images/CancelButton.png" publishTime="08/28/2012 12:09:15" />
    <file relUrl="bin/ReportBuilderAjax.Web.XmlSerializers.dll" publishTime="08/28/2012 21:45:06" />
    <file relUrl="images/bottom_combobox_bg.png" publishTime="08/28/2012 12:09:14" />
    <file relUrl="js/Common/ControlLibrary/ControlAbstractClassPrototypeCustomize.js" publishTime="08/28/2012 12:09:15" />
    <file relUrl="images/directory_tree_last.png" publishTime="08/28/2012 12:09:15" />
    <file relUrl="Global.asax" publishTime="08/28/2012 12:09:21" />
    <file relUrl="images/unchecked.png" publishTime="08/28/2012 12:09:15" />
    <file relUrl="images/uploadButton.png" publishTime="08/28/2012 12:09:15" />
    <file relUrl="js/Common/KeyTable.js" publishTime="08/28/2012 12:09:16" />
    <file relUrl="Templates/ReleaseNotesTemplate.htm" publishTime="08/28/2012 12:09:13" />
    <file relUrl="images/bottom_right.png" publishTime="08/28/2012 12:09:15" />
    <file relUrl="images/standart_folder.png" publishTime="08/28/2012 12:09:15" />
    <file relUrl="images/ScrollRightIcon.png" publishTime="08/28/2012 12:09:15" />
    <file relUrl="images/top_right_active_report_fields.png" publishTime="08/28/2012 12:09:15" />
    <file relUrl="bin/Microsoft.Practices.ObjectBuilder2.dll" publishTime="08/28/2012 12:09:23" />
    <file relUrl="images/as_grid_button_Add_Recipients.png" publishTime="08/28/2012 12:09:15" />
    <file relUrl="images/SaveReportAsNewButton.png" publishTime="08/28/2012 12:09:15" />
    <file relUrl="images/top_left_hover_blue_report.png" publishTime="08/28/2012 12:09:15" />
    <file relUrl="js/Common/Plupload/jquery.plupload.queue.min.js" publishTime="08/28/2012 12:09:15" />
    <file relUrl="images/directory_tree.png" publishTime="08/28/2012 12:09:15" />
    <file relUrl="images/blue_delete_button.png" publishTime="08/28/2012 12:09:15" />
    <file relUrl="images/right_corner_tab_sheduler_active.png" publishTime="08/28/2012 12:09:15" />
    <file relUrl="js/Common/ControlLibrary/RadioButtonSetControl.js" publishTime="08/28/2012 12:09:15" />
    <file relUrl="js/ActivityControl.js" publishTime="08/28/2012 12:09:16" />
    <file relUrl="js/Common/jquery-ui-1.7.3.custom.min.js" publishTime="08/28/2012 12:09:15" />
    <file relUrl="images/prevReportBtn.png" publishTime="08/28/2012 12:09:15" />
    <file relUrl="images/DropDownLeft2.png" publishTime="08/28/2012 12:09:15" />
    <file relUrl="images/as_main_bottom.png" publishTime="08/28/2012 12:09:15" />
    <file relUrl="images/YellowMinusButton.png" publishTime="08/28/2012 12:09:15" />
    <file relUrl="images/CheckBoxInactive.png" publishTime="08/28/2012 12:09:15" />
    <file relUrl="images/LeftLastXDays.png" publishTime="08/28/2012 12:09:15" />
    <file relUrl="Templates/ReportTabs.htm" publishTime="08/28/2012 14:41:51" />
    <file relUrl="js/Common/RegionPlugin.js" publishTime="08/28/2012 12:09:16" />
    <file relUrl="images/sort_asc.png" publishTime="08/28/2012 12:09:14" />
    <file relUrl="Templates/ReportLayoutGrouping.htm" publishTime="08/28/2012 12:09:13" />
    <file relUrl="images/background_select_DropDown.png" publishTime="08/28/2012 12:09:15" />
    <file relUrl="images/MiddleHeaderShadow.png" publishTime="08/28/2012 12:09:15" />
    <file relUrl="images/bottom_hover_blue_report.png" publishTime="08/28/2012 12:09:15" />
    <file relUrl="images/Clear.png" publishTime="08/28/2012 12:09:15" />
    <file relUrl="images/as_grid3_top.png" publishTime="08/28/2012 12:09:14" />
    <file relUrl="images/BackButton.png" publishTime="08/28/2012 12:09:15" />
    <file relUrl="js/Common/ControlLibrary/DropDownControl.js" publishTime="08/28/2012 12:09:16" />
    <file relUrl="images/RightWhiteBttn.png" publishTime="08/28/2012 12:09:15" />
    <file relUrl="js/Filters/LossRunSummaryFilter.js" publishTime="08/28/2012 12:09:16" />
    <file relUrl="images/DropDown_right_bottom_radius.png" publishTime="08/28/2012 12:09:15" />
    <file relUrl="images/top_left_hover_bg_report.png" publishTime="08/28/2012 12:09:15" />
    <file relUrl="images/combobox_filter_bg.png" publishTime="08/28/2012 12:09:15" />
    <file relUrl="images/ViewReport.png" publishTime="08/28/2012 12:09:15" />
    <file relUrl="Login.aspx" publishTime="08/28/2012 14:41:51" />
    <file relUrl="images/RadioActive2.png" publishTime="08/28/2012 12:09:14" />
    <file relUrl="images/LeftWhiteTab.png" publishTime="08/28/2012 12:09:15" />
    <file relUrl="js/Common/ControlLibrary/newCheckBoxControl.js" publishTime="08/28/2012 12:09:16" />
    <file relUrl="images/DropDownArrowDown.png" publishTime="08/28/2012 12:09:15" />
    <file relUrl="bin/Newtonsoft.Json.dll" publishTime="08/28/2012 12:09:23" />
    <file relUrl="css/ui-lightness/images/ui-bg_highlight-soft_100_eeeeee_1x100.png" publishTime="08/28/2012 12:09:16" />
    <file relUrl="js/SummarizeFields.js" publishTime="08/28/2012 12:09:16" />
    <file relUrl="images/as_main_top.png" publishTime="08/28/2012 12:09:15" />
    <file relUrl="images/RightBlackBttn2.png" publishTime="08/28/2012 12:09:15" />
    <file relUrl="images/as_grid_comment_input_center.png" publishTime="08/28/2012 12:09:15" />
    <file relUrl="js/Common/jquery.maskedinput-1.2.1.js" publishTime="08/28/2012 12:09:16" />
    <file relUrl="images/RadioActive.png" publishTime="08/28/2012 12:09:15" />
    <file relUrl="Templates/DeliveredReportTemplate.htm" publishTime="08/28/2012 14:41:51" />
    <file relUrl="js/ReportLayoutGrouping.js" publishTime="08/28/2012 12:09:16" />
    <file relUrl="js/ReportCustomLogo.js" publishTime="08/28/2012 12:09:16" />
    <file relUrl="images/left_numder_history_page.png" publishTime="08/28/2012 12:09:15" />
    <file relUrl="images/GrayPuzzleIcon.png" publishTime="08/28/2012 12:09:15" />
    <file relUrl="images/grid.png" publishTime="08/28/2012 12:09:15" />
    <file relUrl="images/YellowPlayButton.png" publishTime="08/28/2012 12:09:14" />
    <file relUrl="Fonts/semibold/MyriadPro-Semibold.woff" publishTime="08/28/2012 12:09:18" />
    <file relUrl="js/Common/jquery.ui.datepicker.min.js" publishTime="08/28/2012 12:09:15" />
    <file relUrl="js/Common/Timer.js" publishTime="08/28/2012 12:09:15" />
    <file relUrl="images/CollapsedBottomLeftMain.png" publishTime="08/28/2012 12:09:15" />
    <file relUrl="images/DropDown_bottom_border.png" publishTime="08/28/2012 12:09:15" />
    <file relUrl="images/border_left.png" publishTime="08/28/2012 12:09:15" />
    <file relUrl="images/DropDown_left_top_radius.png" publishTime="08/28/2012 12:09:14" />
    <file relUrl="js/ReportTabManager.js" publishTime="08/28/2012 12:09:16" />
    <file relUrl="images/SaveReportButton.png" publishTime="08/28/2012 12:09:15" />
    <file relUrl="images/right_dotted_border.png" publishTime="08/28/2012 12:09:14" />
    <file relUrl="js/Common/ControlLibrary/StaticControl.js" publishTime="08/28/2012 12:09:15" />
    <file relUrl="images/ClearFilter2.png" publishTime="08/28/2012 12:09:15" />
    <file relUrl="images/InputCalendarSelected.png" publishTime="08/28/2012 12:09:15" />
    <file relUrl="images/top_right_group.png" publishTime="08/28/2012 12:09:15" />
    <file relUrl="js/Common/jquery.history.js" publishTime="08/28/2012 12:09:15" />
    <file relUrl="Fonts/regular/MyriadPro-Regular.svg" publishTime="08/28/2012 12:09:19" />
    <file relUrl="images/HeaderMiddleBackground.png" publishTime="08/28/2012 12:09:14" />
    <file relUrl="images/top_right_hover_bg_report.png" publishTime="08/28/2012 12:09:15" />
    <file relUrl="images/bottom_left_dotted_border.png" publishTime="08/28/2012 12:09:14" />
    <file relUrl="images/right_corner_combobox.png" publishTime="08/28/2012 12:09:15" />
    <file relUrl="css/ui-lightness/jquery.ui.datepicker.css" publishTime="08/28/2012 12:09:16" />
    <file relUrl="images/viewReportPDFImage.png" publishTime="08/28/2012 12:09:15" />
    <file relUrl="Templates/ReportBuilderHeader.htm" publishTime="08/28/2012 12:09:13" />
    <file relUrl="js/DeliveredReports.js" publishTime="08/28/2012 14:41:51" />
    <file relUrl="images/viewReportEXImage.png" publishTime="08/28/2012 12:09:15" />
    <file relUrl="images/top_left_group.png" publishTime="08/28/2012 12:09:15" />
    <file relUrl="images/top_left.png" publishTime="08/28/2012 12:09:15" />
    <file relUrl="images/Minus.png" publishTime="08/28/2012 12:09:15" />
    <file relUrl="images/LeftBlackTab2.png" publishTime="08/28/2012 12:09:15" />
    <file relUrl="images/reportPageLeftSide.png" publishTime="08/28/2012 12:09:15" />
    <file relUrl="images/xlsWhite.png" publishTime="08/28/2012 12:09:15" />
    <file relUrl="js/Common/CrossBrowseElement.js" publishTime="08/28/2012 12:09:15" />
    <file relUrl="images/MainRightShadow.png" publishTime="08/28/2012 12:09:15" />
    <file relUrl="Fonts/ptsans/PTSans-NarrowBold.eot" publishTime="08/28/2012 12:09:21" />
    <file relUrl="js/DragDropFields.js" publishTime="08/28/2012 12:09:16" />
    <file relUrl="images/exportPDFReport.png" publishTime="08/28/2012 12:09:15" />
    <file relUrl="images/exporXLSReport.png" publishTime="08/28/2012 12:09:14" />
    <file relUrl="images/black_left_sort.png" publishTime="08/28/2012 12:09:15" />
    <file relUrl="images/right_numder_history_page.png" publishTime="08/28/2012 12:09:15" />
    <file relUrl="Fonts/myriadpro-bold-webfont.ttf" publishTime="08/28/2012 12:09:18" />
    <file relUrl="images/as_grid_input_right.png" publishTime="08/28/2012 12:09:14" />
    <file relUrl="images/bg_active_history_report_row.png" publishTime="08/28/2012 12:09:15" />
    <file relUrl="Templates/ReportBuilderMain.htm" publishTime="08/28/2012 12:09:13" />
    <file relUrl="DownloadFile.aspx" publishTime="08/28/2012 12:09:12" />
    <file relUrl="images/login_input_username_text.png" publishTime="08/28/2012 12:09:15" />
    <file relUrl="Templates/CheckpointsConfigurationTemplate.htm" publishTime="08/28/2012 12:09:13" />
    <file relUrl="images/hover_folder.png" publishTime="08/28/2012 12:09:15" />
    <file relUrl="images/combobox_options_left_bg.png" publishTime="08/28/2012 12:09:15" />
    <file relUrl="images/bottom_dotted_border.png" publishTime="08/28/2012 12:09:15" />
    <file relUrl="bin/Microsoft.ReportingServices.RdlObjectModel.dll" publishTime="08/28/2012 12:09:23" />
    <file relUrl="js/Common/TemplateEngine.js" publishTime="08/28/2012 12:09:16" />
    <file relUrl="images/left_corner_tab_inactive.png" publishTime="08/28/2012 12:09:15" />
    <file relUrl="images/SwitchClient.png" publishTime="08/28/2012 12:09:15" />
    <file relUrl="images/reportPageRightSide.png" publishTime="08/28/2012 12:09:15" />
    <file relUrl="css/ui-lightness/images/ui-icons_ffd27a_256x240.png" publishTime="08/28/2012 12:09:16" />
    <file relUrl="images/center_grey_trans_bg.png" publishTime="08/28/2012 12:09:15" />
    <file relUrl="images/right_grey_trans_bg.png" publishTime="08/28/2012 12:09:14" />
    <file relUrl="css/ui-lightness/images/ui-bg_gloss-wave_35_f6a828_500x100.png" publishTime="08/28/2012 12:09:16" />
    <file relUrl="images/top_filter_schedule_bg.png" publishTime="08/28/2012 12:09:15" />
    <file relUrl="images/DropDown_filter_top_border.png" publishTime="08/28/2012 12:09:15" />
    <file relUrl="images/border_right.png" publishTime="08/28/2012 12:09:15" />
    <file relUrl="images/DropDown_left_border.png" publishTime="08/28/2012 12:09:15" />
    <file relUrl="js/Common/ControlLibrary/ControlAbstractClass.js" publishTime="08/28/2012 12:09:16" />
    <file relUrl="images/radio_center_white3.png" publishTime="08/28/2012 12:09:15" />
    <file relUrl="images/switchClient_popin_body.png" publishTime="08/28/2012 12:09:15" />
    <file relUrl="images/top_center_active_bg_report.png" publishTime="08/28/2012 12:09:14" />
    <file relUrl="images/bottom_right_dotted_border.png" publishTime="08/28/2012 12:09:15" />
    <file relUrl="js/Common/Common.js" publishTime="08/28/2012 12:09:15" />
    <file relUrl="images/YellowPencilButton.png" publishTime="08/28/2012 12:09:15" />
    <file relUrl="css/ui-lightness/images/ui-icons_228ef1_256x240.png" publishTime="08/28/2012 12:09:16" />
    <file relUrl="images/BottomMainBg2.png" publishTime="08/28/2012 12:09:15" />
    <file relUrl="images/as_grid4_top.png" publishTime="08/28/2012 12:09:15" />
    <file relUrl="images/checked.png" publishTime="08/28/2012 12:09:15" />
    <file relUrl="bin/Microsoft.Practices.EnterpriseLibrary.Common.dll" publishTime="08/28/2012 12:09:23" />
    <file relUrl="Fonts/ptn77f-webfont.woff" publishTime="08/28/2012 12:09:18" />
    <file relUrl="js/Common/ControlLibrary/DinamicRadioButtonSetControl.js" publishTime="08/28/2012 12:09:16" />
    <file relUrl="js/Common/ControlLibrary/MultiRadioButton.js" publishTime="08/28/2012 12:09:15" />
    <file relUrl="Style.css" publishTime="08/28/2012 14:41:51" />
    <file relUrl="js/Common/ControlLibrary/DateTimeControl.js" publishTime="08/28/2012 12:09:16" />
    <file relUrl="images/combobox_options_right_bg.png" publishTime="08/28/2012 12:09:15" />
    <file relUrl="Fonts/myriadpro-bold-webfont.eot" publishTime="08/28/2012 12:09:21" />
    <file relUrl="images/LeftBlackBttn.png" publishTime="08/28/2012 12:09:15" />
    <file relUrl="images/TopHeader.png" publishTime="08/28/2012 12:09:15" />
    <file relUrl="images/as_grid4_bottom.png" publishTime="08/28/2012 12:09:14" />
    <file relUrl="images/CollapsedTopLeftMain.png" publishTime="08/28/2012 12:09:15" />
    <file relUrl="images/tab_active_bg.png" publishTime="08/28/2012 12:09:15" />
    <file relUrl="css/ui-lightness/jquery-ui-timepicker-addon.css" publishTime="08/28/2012 12:09:16" />
    <file relUrl="Fonts/MyriadPro-Semibold.otf" publishTime="08/28/2012 12:09:18" />
    <file relUrl="CompanyLogo/compmc.png" publishTime="08/28/2012 12:09:16" />
    <file relUrl="images/exampleButton.png" publishTime="08/28/2012 12:09:15" />
    <file relUrl="images/emptyLogoButton.png" publishTime="08/28/2012 12:09:15" />
    <file relUrl="images/Plus.png" publishTime="08/28/2012 12:09:15" />
    <file relUrl="Templates/DragDropFields.htm" publishTime="08/28/2012 12:09:13" />
    <file relUrl="images/top_combobox_bg.png" publishTime="08/28/2012 12:09:15" />
    <file relUrl="images/pdfBlack.png" publishTime="08/28/2012 12:09:15" />
    <file relUrl="js/ReportLayoutColumns.js" publishTime="08/28/2012 12:09:15" />
    <file relUrl="images/browseButton.png" publishTime="08/28/2012 12:09:14" />
    <file relUrl="images/DropDown_filter_left_top_radius.png" publishTime="08/28/2012 12:09:15" />
    <file relUrl="images/icon_PDF.png" publishTime="08/28/2012 12:09:15" />
    <file relUrl="images/bottom_left_hover_blue_report.png" publishTime="08/28/2012 12:09:15" />
    <file relUrl="CompanyLogo/ccmsi1.png" publishTime="08/28/2012 12:09:16" />
    <file relUrl="images/right_corner_top_sheduler.png" publishTime="08/28/2012 12:09:14" />
    <file relUrl="Fonts/regular/MyriadPro-Regular.woff" publishTime="08/28/2012 12:09:19" />
    <file relUrl="images/left_grey_trans_bg.png" publishTime="08/28/2012 12:09:14" />
    <file relUrl="js/Common/jquery-ui-timepicker-addon.js" publishTime="08/28/2012 12:09:15" />
    <file relUrl="images/LeftBlackTab.png" publishTime="08/28/2012 12:09:14" />
    <file relUrl="images/right_change_field_name.png" publishTime="08/28/2012 12:09:15" />
    <file relUrl="images/left_corner_down_schedule_filter.png" publishTime="08/28/2012 12:09:14" />
    <file relUrl="images/mainBg.gif" publishTime="08/28/2012 12:09:15" />
    <file relUrl="js/Common/Silverlight.js" publishTime="08/28/2012 12:09:16" />
    <file relUrl="js/CheckpointsConfiguration.js" publishTime="08/28/2012 12:09:16" />
    <file relUrl="images/right_corner_group_inactive.png" publishTime="08/28/2012 12:09:15" />
    <file relUrl="Fonts/regular/MyriadPro-Regular.afm" publishTime="08/28/2012 12:09:19" />
    <file relUrl="images/SwitchClientIcon.png" publishTime="08/28/2012 12:09:14" />
    <file relUrl="bin/ReportBuilderAjax.Web.Common.pdb" publishTime="08/28/2012 21:45:03" />
    <file relUrl="images/RightTopMainBorder.png" publishTime="08/28/2012 12:09:15" />
    <file relUrl="Templates/Activity.htm" publishTime="08/28/2012 12:09:13" />
    <file relUrl="images/SaveReportNameInput.png" publishTime="08/28/2012 12:09:15" />
    <file relUrl="images/rn_border.png" publishTime="08/28/2012 12:09:15" />
    <file relUrl="js/Common/Autocomplete.js" publishTime="08/28/2012 12:09:16" />
    <file relUrl="images/rn_attention_img.png" publishTime="08/28/2012 12:09:14" />
    <file relUrl="images/MyReports.png" publishTime="08/28/2012 12:09:15" />
    <file relUrl="images/HeaderBackground.png" publishTime="08/28/2012 12:09:14" />
    <file relUrl="images/top_left_active_report_fields.png" publishTime="08/28/2012 12:09:15" />
    <file relUrl="images/login_button_sign.png" publishTime="08/28/2012 12:09:15" />
    <file relUrl="bin/Microsoft.Practices.EnterpriseLibrary.Logging.dll" publishTime="08/28/2012 12:09:23" />
    <file relUrl="images/ShowAll.png" publishTime="08/28/2012 12:09:15" />
    <file relUrl="Templates/Hierarchy.htm" publishTime="08/28/2012 12:09:13" />
    <file relUrl="images/CheckBoxActive.png" publishTime="08/28/2012 12:09:15" />
    <file relUrl="images/left_change_field_name.png" publishTime="08/28/2012 12:09:15" />
    <file relUrl="images/rn_select_row.png" publishTime="08/28/2012 12:09:15" />
    <file relUrl="images/BasicFilterArreyUp.png" publishTime="08/28/2012 12:09:15" />
    <file relUrl="images/CenterBlackTab.png" publishTime="08/28/2012 12:09:15" />
    <file relUrl="images/RightWhiteTab.png" publishTime="08/28/2012 12:09:15" />
    <file relUrl="js/Common/Plupload/plupload.flash.swf" publishTime="08/28/2012 12:09:15" />
    <file relUrl="Fonts/ptsans/PTSans-NarrowBold.svg" publishTime="08/28/2012 12:09:21" />
    <file relUrl="images/center_left.png" publishTime="08/28/2012 12:09:14" />
    <file relUrl="images/reportPrintBg.png" publishTime="08/28/2012 12:09:15" />
    <file relUrl="images/rightBg.png" publishTime="08/28/2012 12:09:15" />
    <file relUrl="images/LeftSideButton.png" publishTime="08/28/2012 12:09:15" />
    <file relUrl="images/PdfIcon2.png" publishTime="08/28/2012 12:09:15" />
    <file relUrl="images/as_grid_input_center.png" publishTime="08/28/2012 12:09:15" />
    <file relUrl="images/top_line_group.png" publishTime="08/28/2012 12:09:15" />
    <file relUrl="images/BlackGradientTabBg.png" publishTime="08/28/2012 12:09:15" />
    <file relUrl="Fonts/semibold/MyriadPro-Semibold.ttf" publishTime="08/28/2012 12:09:18" />
    <file relUrl="images/right_corner_filter_textbox.png" publishTime="08/28/2012 12:09:15" />
    <file relUrl="Fonts/myriadpro-semibold-webfont.eot" publishTime="08/28/2012 12:09:18" />
    <file relUrl="images/right_corner_bottom_sheduler.png" publishTime="08/28/2012 12:09:15" />
    <file relUrl="Fonts/regular/MyriadPro-Regular.eot" publishTime="08/28/2012 12:09:19" />
    <file relUrl="css/ui-lightness/images/ui-bg_flat_10_000000_40x100.png" publishTime="08/28/2012 12:09:16" />
    <file relUrl="images/LeftWhiteBttn2.png" publishTime="08/28/2012 12:09:14" />
    <file relUrl="images/GrayPlusButton.png" publishTime="08/28/2012 12:09:15" />
    <file relUrl="HttpHandlers/RdlService.svc" publishTime="08/28/2012 12:09:13" />
    <file relUrl="js/Common/json2.js" publishTime="08/28/2012 12:09:16" />
    <file relUrl="images/bottom_sheduler_bg.png" publishTime="08/28/2012 12:09:15" />
    <file relUrl="js/ReportSelectForm.js" publishTime="08/28/2012 14:41:51" />
    <file relUrl="images/bottom_right_active_report_fields.png" publishTime="08/28/2012 12:09:15" />
    <file relUrl="images/tab_inactive_bg.png" publishTime="08/28/2012 12:09:15" />
    <file relUrl="images/close_group_column.png" publishTime="08/28/2012 12:09:15" />
    <file relUrl="images/ScheduleCalendar.png" publishTime="08/28/2012 12:09:15" />
    <file relUrl="js/Common/ControlLibrary/EventFunctionSetClass.js" publishTime="08/28/2012 12:09:16" />
    <file relUrl="js/Common/jquery.extend.centerElement.js" publishTime="08/28/2012 12:09:16" />
    <file relUrl="images/LeftWhiteLoginBttn.png" publishTime="08/28/2012 12:09:15" />
    <file relUrl="images/open_folder.png" publishTime="08/28/2012 12:09:14" />
    <file relUrl="images/left_corner_tab_shedule.png" publishTime="08/28/2012 12:09:15" />
    <file relUrl="images/RunReportButton.png" publishTime="08/28/2012 12:09:15" />
    <file relUrl="images/as_main_button_Cancel.png" publishTime="08/28/2012 12:09:15" />
    <file relUrl="images/rn_bottom_border.png" publishTime="08/28/2012 12:09:14" />
    <file relUrl="images/RunReport.png" publishTime="08/28/2012 12:09:15" />
    <file relUrl="js/Common/ControlLibrary/MultiSelectComboBox.js" publishTime="08/28/2012 12:09:15" />
    <file relUrl="images/left_corner_shedule_filter.png" publishTime="08/28/2012 12:09:15" />
    <file relUrl="js/FilterBase.js" publishTime="08/28/2012 12:09:16" />
    <file relUrl="images/DropDown_top_border.png" publishTime="08/28/2012 12:09:15" />
    <file relUrl="images/BorderBottomLeft.png" publishTime="08/28/2012 12:09:15" />
    <file relUrl="images/CenterDropDown2.png" publishTime="08/28/2012 12:09:15" />
    <file relUrl="images/group_inactive_bg.png" publishTime="08/28/2012 12:09:15" />
    <file relUrl="images/LoginBackground.png" publishTime="08/28/2012 12:09:15" />
    <file relUrl="images/CenterWhiteBttn.png" publishTime="08/28/2012 12:09:15" />
    <file relUrl="images/LeftMainBg.png" publishTime="08/28/2012 12:09:15" />
    <file relUrl="images/right_corner_schedule_filter.png" publishTime="08/28/2012 12:09:14" />
    <file relUrl="images/dropDownCenter.png" publishTime="08/28/2012 12:09:15" />
    <file relUrl="css/ui-lightness/images/ui-icons_ef8c08_256x240.png" publishTime="08/28/2012 12:09:16" />
    <file relUrl="images/GrayPencilIcon.png" publishTime="08/28/2012 12:09:15" />
    <file relUrl="images/CenterButton.png" publishTime="08/28/2012 12:09:15" />
    <file relUrl="images/RightWhiteTab2.png" publishTime="08/28/2012 12:09:14" />
    <file relUrl="Fonts/semibold/MyriadPro-Semibold.svg" publishTime="08/28/2012 12:09:18" />
    <file relUrl="images/BlackGridBg2.png" publishTime="08/28/2012 12:09:15" />
    <file relUrl="images/tab_sheduler_bg_active.png" publishTime="08/28/2012 12:09:15" />
    <file relUrl="js/ScheduleRecipientsFilter.js" publishTime="08/28/2012 12:09:16" />
    <file relUrl="js/Common/Plupload/plupload.full.min.js" publishTime="08/28/2012 12:09:15" />
    <file relUrl="css/ui-lightness/images/ui-bg_glass_100_f6f6f6_1x400.png" publishTime="08/28/2012 12:09:16" />
    <file relUrl="images/reportPageBgSide.png" publishTime="08/28/2012 12:09:15" />
    <file relUrl="images/closed_folder.png" publishTime="08/28/2012 12:09:15" />
    <file relUrl="images/RightBottomMainBorder.png" publishTime="08/28/2012 12:09:15" />
    <file relUrl="images/center_change_field_name.png" publishTime="08/28/2012 12:09:15" />
    <file relUrl="images/RightYellowBttn.png" publishTime="08/28/2012 12:09:15" />
    <file relUrl="HttpHandlers/ReportGenerationService.svc" publishTime="08/28/2012 12:09:13" />
    <file relUrl="js/ViewReport.js" publishTime="08/28/2012 14:41:51" />
    <file relUrl="images/icon_XLS.png" publishTime="08/28/2012 12:09:15" />
    <file relUrl="images/ScheduleTimeCalendar.png" publishTime="08/28/2012 12:09:15" />
    <file relUrl="images/RightMiddleMainBg.png" publishTime="08/28/2012 12:09:14" />
    <file relUrl="images/RightSideButton.png" publishTime="08/28/2012 12:09:14" />
    <file relUrl="js/Common/ControlLibrary/ClassInheritance.js" publishTime="08/28/2012 12:09:15" />
    <file relUrl="Templates/CustomLogoReport.htm" publishTime="08/28/2012 12:09:13" />
    <file relUrl="css/ui-lightness/images/ui-icons_ffffff_256x240.png" publishTime="08/28/2012 12:09:16" />
    <file relUrl="Templates/DropDownTemplates.htm" publishTime="08/28/2012 12:09:13" />
    <file relUrl="images/as_grid_bottom.png" publishTime="08/28/2012 12:09:15" />
    <file relUrl="images/left_corner_group_active.png" publishTime="08/28/2012 12:09:14" />
    <file relUrl="images/bottom_center_active_bg_report.png" publishTime="08/28/2012 12:09:15" />
    <file relUrl="images/CenterSaveBttn.png" publishTime="08/28/2012 12:09:14" />
    <file relUrl="images/focus_item.png" publishTime="08/28/2012 12:09:14" />
    <file relUrl="images/CenterBlackBttn.png" publishTime="08/28/2012 12:09:15" />
    <file relUrl="images/bottom_left_hover_bg_report.png" publishTime="08/28/2012 12:09:15" />
    <file relUrl="Templates/ReportLayoutColumns.htm" publishTime="08/28/2012 12:09:13" />
    <file relUrl="js/ReportBuilderHeader.js" publishTime="08/28/2012 12:09:16" />
    <file relUrl="images/CollapsedCenterLeftMain.png" publishTime="08/28/2012 12:09:15" />
    <file relUrl="bin/ReportBuilderAjax.Web.pdb" publishTime="08/28/2012 21:45:05" />
    <file relUrl="images/CenterLastXDays.png" publishTime="08/28/2012 12:09:14" />
    <file relUrl="images/as_clock.png" publishTime="08/28/2012 12:09:15" />
    <file relUrl="Fonts/ptsans/PTSans-NarrowBold.woff" publishTime="08/28/2012 12:09:21" />
    <file relUrl="images/DropDown_right_border.png" publishTime="08/28/2012 12:09:14" />
    <file relUrl="js/Common/jquery.dataTables.js" publishTime="08/28/2012 12:09:15" />
    <file relUrl="images/LeftSaveBttn.png" publishTime="08/28/2012 12:09:15" />
    <file relUrl="images/GrayXIcon.png" publishTime="08/28/2012 12:09:15" />
    <file relUrl="images/as_grid_comment_input_right.png" publishTime="08/28/2012 12:09:15" />
    <file relUrl="images/login_Logo.png" publishTime="08/28/2012 12:09:15" />
    <file relUrl="images/as_grid_header.png" publishTime="08/28/2012 12:09:15" />
    <file relUrl="images/InputCalendarDefault.png" publishTime="08/28/2012 12:09:15" />
    <file relUrl="images/checkpoints_save_button.png" publishTime="08/28/2012 12:09:15" />
    <file relUrl="images/CenterYellowBttn.png" publishTime="08/28/2012 12:09:15" />
    <file relUrl="js/Common/ControlLibrary/DateRangeControl.js" publishTime="08/28/2012 12:09:16" />
    <file relUrl="js/ClientAnalysisControl.js" publishTime="08/28/2012 12:09:16" />
    <file relUrl="images/TopMainBg.png" publishTime="08/28/2012 12:09:15" />
    <file relUrl="js/Common/ControlLibrary/CustomDropDown.js" publishTime="08/28/2012 12:09:15" />
    <file relUrl="images/right_corner_as_grid_bottom.png" publishTime="08/28/2012 12:09:15" />
    <file relUrl="images/standart_field_icon.png" publishTime="08/28/2012 12:09:15" />
    <file relUrl="css/ui-lightness/images/ui-bg_glass_100_fdf5ce_1x400.png" publishTime="08/28/2012 12:09:16" />
    <file relUrl="images/open_group_column.png" publishTime="08/28/2012 12:09:15" />
    <file relUrl="Templates/ClientAnalysis.htm" publishTime="08/28/2012 12:09:13" />
    <file relUrl="js/Common/ControlLibrary/StaticDomElement.js" publishTime="08/28/2012 12:09:16" />
    <file relUrl="images/LeftWhiteBttn.png" publishTime="08/28/2012 12:09:15" />
    <file relUrl="images/refreshReport.png" publishTime="08/28/2012 12:09:14" />
    <file relUrl="images/Cancel.png" publishTime="08/28/2012 12:09:15" />
    <file relUrl="bin/ReportBuilderAjax.Web.Common.dll" publishTime="08/28/2012 21:45:03" />
    <file relUrl="images/removeLogoButton.png" publishTime="08/28/2012 12:09:15" />
    <file relUrl="images/left_corner_top_filter.png" publishTime="08/28/2012 12:09:14" />
    <file relUrl="Fonts/myriadpro-semibold-webfont.woff" publishTime="08/28/2012 12:09:21" />
    <file relUrl="images/BasicFilterArreyDown.png" publishTime="08/28/2012 12:09:15" />
    <file relUrl="css/ui-lightness/images/ui-bg_diagonals-thick_20_666666_40x40.png" publishTime="08/28/2012 12:09:16" />
    <file relUrl="images/bottom_right_hover_bg_report.png" publishTime="08/28/2012 12:09:15" />
    <file relUrl="Fonts/myriadpro-semibold-webfont.svg" publishTime="08/28/2012 12:09:21" />
    <file relUrl="js/ReportBuilderForm.js" publishTime="08/28/2012 12:09:15" />
    <file relUrl="images/right_corner_tab_inactive.png" publishTime="08/28/2012 12:09:15" />
    <file relUrl="images/dropDownRight.png" publishTime="08/28/2012 12:09:15" />
    <file relUrl="js/Common/si.files.js" publishTime="08/28/2012 12:09:15" />
    <file relUrl="images/right_corner_bottom_combobox.png" publishTime="08/28/2012 12:09:15" />
    <file relUrl="js/Common/ControlLibrary/TextAreaControl.js" publishTime="08/28/2012 12:09:15" />
    <file relUrl="js/ReportLayoutSorting.js" publishTime="08/28/2012 12:09:16" />
    <file relUrl="js/Common/ControlLibrary/CalendarControl.js" publishTime="08/28/2012 12:09:15" />
    <file relUrl="images/input_filter_bg.png" publishTime="08/28/2012 12:09:15" />
    <file relUrl="images/DropDown_right_top_radius.png" publishTime="08/28/2012 12:09:14" />
    <file relUrl="HttpHandlers/LogoService.svc" publishTime="08/28/2012 12:09:13" />
    <file relUrl="images/header_tabs_sheduler_bg.png" publishTime="08/28/2012 12:09:14" />
    <file relUrl="js/ShedulerControl.js" publishTime="08/28/2012 12:09:15" />
    <file relUrl="Fonts/ptn77f-webfont.eot" publishTime="08/28/2012 12:09:21" />
    <file relUrl="images/hover_field_icon.png" publishTime="08/28/2012 12:09:15" />
    <file relUrl="Templates/SummarizeFields.htm" publishTime="08/28/2012 12:09:13" />
    <file relUrl="images/LeftBlackBttn2.png" publishTime="08/28/2012 12:09:15" />
    <file relUrl="images/Covered.png" publishTime="08/28/2012 12:09:15" />
    <file relUrl="images/right_corner_down_schedule_filter.png" publishTime="08/28/2012 12:09:15" />
    <file relUrl="images/login_input.png" publishTime="08/28/2012 12:09:14" />
    <file relUrl="images/DataFilters.png" publishTime="08/28/2012 12:09:15" />
    <file relUrl="css/ui-lightness/images/ui-icons_222222_256x240.png" publishTime="08/28/2012 12:09:16" />
    <file relUrl="images/CenterBlackTab2.png" publishTime="08/28/2012 12:09:15" />
    <file relUrl="Templates/ViewReport.htm" publishTime="08/28/2012 12:09:13" />
  </publishProfile>
</publishData>